MANIFEST.in
README.txt
setup.cfg
setup.py
docs/HISTORY.txt
medialog/.DS_Store
medialog/__init__.py
medialog.googlefonts.egg-info/PKG-INFO
medialog.googlefonts.egg-info/SOURCES.txt
medialog.googlefonts.egg-info/dependency_links.txt
medialog.googlefonts.egg-info/entry_points.txt
medialog.googlefonts.egg-info/namespace_packages.txt
medialog.googlefonts.egg-info/not-zip-safe
medialog.googlefonts.egg-info/requires.txt
medialog.googlefonts.egg-info/top_level.txt
medialog/googlefonts/.DS_Store
medialog/googlefonts/__init__.py
medialog/googlefonts/configure.zcml
medialog/googlefonts/interfaces.py
medialog/googlefonts/profiles.zcml
medialog/googlefonts/tests.py
medialog/googlefonts/upgrades.py
medialog/googlefonts/vocabularies.py
medialog/googlefonts/Extensions/Install.py
medialog/googlefonts/browser/__init__.py
medialog/googlefonts/browser/configure.zcml
medialog/googlefonts/browser/fontsheet.pt
medialog/googlefonts/browser/fontsheet_all.pt
medialog/googlefonts/browser/googlefonts_controlpanel_icon.gif
medialog/googlefonts/browser/viewlet.pt
medialog/googlefonts/browser/viewlet.py
medialog/googlefonts/browser/views.py
medialog/googlefonts/profiles/.DS_Store
medialog/googlefonts/profiles/default/.DS_Store
medialog/googlefonts/profiles/default/browserlayer.xml
medialog/googlefonts/profiles/default/cssregistry.xml
medialog/googlefonts/profiles/default/metadata.xml
medialog/googlefonts/profiles/default/registry.xml
medialog/googlefonts/profiles/default/viewlets.xml
medialog/googlefonts/profiles/uninstall/browserlayer.xml
medialog/googlefonts/profiles/uninstall/controlpanel.xml
medialog/googlefonts/profiles/uninstall/cssregistry.xml
medialog/googlefonts/profiles/uninstall/jsregistry.xml
medialog/googlefonts/profiles/uninstall/medialog.subskins.uninstall.txt
medialog/googlefonts/profiles/uninstall/propertiestool.xml
medialog/googlefonts/profiles/uninstall/skins.xml
medialog/googlefonts/profiles/uninstall/viewlets.xml