Metadata-Version: 1.0
Name: medialog.googlefonts
Version: 2.2.2
Summary: Googlefonts for Plone
Home-page: http://medialog.no
Author: Espen Moe-Nilssen
Author-email: espen@medialog.no
License: GPL
Platform: UNKNOWN
Classifier: Programming Language :: Python
Classifier: Topic :: Software Development :: Libraries :: Python Modules
